LICENSE.txt
MANIFEST.in
README.md
setup.json
setup.py
aiida_tbextraction/__init__.py
aiida_tbextraction/_calcfunctions.py
aiida_tbextraction/calculate_tb.py
aiida_tbextraction/fp_tb.py
aiida_tbextraction/optimize_fp_tb.py
aiida_tbextraction/optimize_strained_fp_tb.py
aiida_tbextraction.egg-info/PKG-INFO
aiida_tbextraction.egg-info/SOURCES.txt
aiida_tbextraction.egg-info/dependency_links.txt
aiida_tbextraction.egg-info/entry_points.txt
aiida_tbextraction.egg-info/requires.txt
aiida_tbextraction.egg-info/top_level.txt
aiida_tbextraction/energy_windows/__init__.py
aiida_tbextraction/energy_windows/auto_guess.py
aiida_tbextraction/energy_windows/run_window.py
aiida_tbextraction/energy_windows/window_search.py
aiida_tbextraction/fp_run/__init__.py
aiida_tbextraction/fp_run/_base.py
aiida_tbextraction/fp_run/_qe_run.py
aiida_tbextraction/fp_run/_helpers/__init__.py
aiida_tbextraction/fp_run/_helpers/_calcfunctions.py
aiida_tbextraction/fp_run/reference_bands/__init__.py
aiida_tbextraction/fp_run/reference_bands/_base.py
aiida_tbextraction/fp_run/reference_bands/_qe.py
aiida_tbextraction/fp_run/wannier_input/__init__.py
aiida_tbextraction/fp_run/wannier_input/_base.py
aiida_tbextraction/fp_run/wannier_input/_qe.py
aiida_tbextraction/model_evaluation/__init__.py
aiida_tbextraction/model_evaluation/_band_difference.py
aiida_tbextraction/model_evaluation/_base.py